validata_core/__init__.py
validata_core/cli.py
validata_core/error_messages.py
validata_core/helpers.py
validata_core/structure_warnings.py
validata_core/custom_checks/__init__.py
validata_core/custom_checks/cohesive_columns_value.py
validata_core/custom_checks/compare_columns_value.py
validata_core/custom_checks/french_gps_coordinates.py
validata_core/custom_checks/french_siren_value.py
validata_core/custom_checks/french_siret_value.py
validata_core/custom_checks/missing_required_header.py
validata_core/custom_checks/nomenclature_actes_value.py
validata_core/custom_checks/one_of_required.py
validata_core/custom_checks/opening_hours_value.py
validata_core/custom_checks/phone_number_value.py
validata_core/custom_checks/sum_columns_value.py
validata_core/custom_checks/utils.py
validata_core/custom_checks/year_interval_value.py
validata_core-0.9.7.dist-info/LICENSE
validata_core-0.9.7.dist-info/METADATA
validata_core-0.9.7.dist-info/WHEEL
validata_core-0.9.7.dist-info/entry_points.txt
validata_core-0.9.7.dist-info/top_level.txt
validata_core-0.9.7.dist-info/zip-safe
validata_core-0.9.7.dist-info/RECORD
