Metadata-Version: 2.1
Name: validata-core
Version: 0.9.7
Summary: Validata Core library
Home-page: https://git.opendatafrance.net/validata/validata-core/
Author: Validata team
Author-email: admin-validata@jailbreak.paris
License: AGPLv3
Platform: UNKNOWN
Classifier: Development Status :: 5 - Production/Stable
Classifier: Intended Audience :: Developers
Classifier: Topic :: Software Development :: Libraries :: Python Modules
Classifier: Operating System :: OS Independent
Classifier: License :: OSI Approved :: GNU Affero General Public License v3
Classifier: Programming Language :: Python :: 3
License-File: LICENSE
Requires-Dist: ezodf
Requires-Dist: frictionless[excel] ==4.38.0
Requires-Dist: importlib-resources
Requires-Dist: openpyxl
Requires-Dist: lxml
Requires-Dist: requests
Requires-Dist: tablib[pandas]
Requires-Dist: toolz
Requires-Dist: opening-hours-py ==0.6.17
Requires-Dist: phonenumbers
Requires-Dist: python-stdnum
Requires-Dist: shapely
